nerualpha/IBridge.py
nerualpha/INeru.py
nerualpha/__init__.py
nerualpha/bridge.py
nerualpha/neru.py
nerualpha/providers/__init__.py
nerualpha/providers/assets/IAssets.py
nerualpha/providers/assets/__init__.py
nerualpha/providers/assets/assets.py
nerualpha/providers/assets/assetsActions.py
nerualpha/providers/assets/contracts/__init__.py
nerualpha/providers/assets/contracts/assetInfo.py
nerualpha/providers/assets/contracts/assetLinkResponse.py
nerualpha/providers/assets/contracts/assetListResponse.py
nerualpha/providers/assets/contracts/directoryPayload.py
nerualpha/providers/assets/contracts/getAssetPayload.py
nerualpha/providers/assets/contracts/getAssetResponse.py
nerualpha/providers/assets/contracts/linkPayload.py
nerualpha/providers/assets/contracts/listAssetsPayload.py
nerualpha/providers/assets/contracts/removeAssetPayload.py
nerualpha/providers/assets/fileRetentionPeriod.py
nerualpha/providers/events/IEventEmitter.py
nerualpha/providers/events/IEventFactory.py
nerualpha/providers/events/INeruEvent.py
nerualpha/providers/events/ISessionCreatedDetails.py
nerualpha/providers/events/__init__.py
nerualpha/providers/events/eventEmitter.py
nerualpha/providers/events/eventFactory.py
nerualpha/providers/events/neruEvent.py
nerualpha/providers/events/neruEventSourceTypes.py
nerualpha/providers/events/neruEventTypes.py
nerualpha/providers/events/sessionCreatedDetails.py
nerualpha/providers/logger/ILogAction.py
nerualpha/providers/logger/ILogContext.py
nerualpha/providers/logger/ILogger.py
nerualpha/providers/logger/__init__.py
nerualpha/providers/logger/logAction.py
nerualpha/providers/logger/logContext.py
nerualpha/providers/logger/logLevels.py
nerualpha/providers/logger/logger.py
nerualpha/providers/logger/sourceTypes.py
nerualpha/providers/meetings/__init__.py
nerualpha/providers/meetings/contracts/ICreateRoomPayload.py
nerualpha/providers/meetings/contracts/__init__.py
nerualpha/providers/meetings/contracts/createRoomPayload.py
nerualpha-5.1.0.dist-info/METADATA
nerualpha-5.1.0.dist-info/WHEEL
nerualpha-5.1.0.dist-info/RECORD
