Metadata-Version: 2.1
Name: nerualpha
Version: 5.1.0
Summary: neru-sdk for python developers
License: MIT
Author: Sergei Rastrigin
Author-email: sergei.rastrigin@vonage.com
Requires-Python: >=3.10.5,<4.0.0
Classifier: License :: OSI Approved :: MIT License
Classifier: Programming Language :: Python :: 3
Classifier: Programming Language :: Python :: 3.11
Classifier: Programming Language :: Python :: 3.12
Requires-Dist: PyJWT[crypto]
Requires-Dist: aiohttp
Requires-Dist: pendulum
Requires-Dist: requests
